mfbatch/__init__.py
mfbatch/__main__.py
mfbatch/commands.py
mfbatch/metaflac.py
mfbatch/util.py
mfbatch-0.6.0.dist-info/LICENSE
mfbatch-0.6.0.dist-info/METADATA
mfbatch-0.6.0.dist-info/WHEEL
mfbatch-0.6.0.dist-info/entry_points.txt
mfbatch-0.6.0.dist-info/RECORD
