Metadata-Version: 2.3
Name: mfbatch
Version: 0.6.0
Summary: MetaFlac batch editor
License: MIT
Keywords: flac,metadata,audio,multimedia,console,scripting
Author: Jamie Hardt
Author-email: jamiehardt@me.com
Requires-Python: >=3.9,<4.0
Classifier: Development Status :: 4 - Beta
Classifier: Environment :: Console
Classifier: License :: OSI Approved :: MIT License
Classifier: Programming Language :: Python :: 3
Classifier: Programming Language :: Python :: 3.9
Classifier: Programming Language :: Python :: 3.10
Classifier: Programming Language :: Python :: 3.11
Classifier: Programming Language :: Python :: 3.12
Classifier: Programming Language :: Python :: 3.13
Classifier: Topic :: Multimedia :: Sound/Audio :: Editors
Requires-Dist: tqdm (>=4.66.4,<5.0.0)
Project-URL: Homepage, https://github.com/iluvcapra/mfbatch
Project-URL: Repository, https://github.com/iluvcapra/mfbatch.git
